{".class": "MypyFile", "_fullname": "NetworkCrafter", "is_partial_stub_package": false, "is_stub": false, "names": {".class": "SymbolTable", "Network": {".class": "SymbolTableNode", "cross_ref": "Precompiler.Network", "kind": "Gdef"}, "__doc__": {".class": "SymbolTableNode", "kind": "Gdef", "node": {".class": "Var", "flags": ["is_ready"], "fullname": "NetworkCrafter.__doc__", "name": "__doc__", "type": "builtins.str"}}, "__file__": {".class": "SymbolTableNode", "kind": "Gdef", "node": {".class": "Var", "flags": ["is_ready"], "fullname": "NetworkCrafter.__file__", "name": "__file__", "type": "builtins.str"}}, "__name__": {".class": "SymbolTableNode", "kind": "Gdef", "node": {".class": "Var", "flags": ["is_ready"], "fullname": "NetworkCrafter.__name__", "name": "__name__", "type": "builtins.str"}}, "__package__": {".class": "SymbolTableNode", "kind": "Gdef", "node": {".class": "Var", "flags": ["is_ready"], "fullname": "NetworkCrafter.__package__", "name": "__package__", "type": "builtins.str"}}, "calculateFaucets": {".class": "SymbolTableNode", "cross_ref": "Precompiler.calculateFaucets", "kind": "Gdef"}, "calculateUpstreamDistances": {".class": "SymbolTableNode", "cross_ref": "Precompiler.calculateUpstreamDistances", "kind": "Gdef"}, "generateNetwork": {".class": "SymbolTableNode", "kind": "Gdef", "node": {".class": "FuncDef", "arg_kinds": [0], "arg_names": ["fp"], "flags": [], "fullname": "NetworkCrafter.generateNetwork", "name": "generateNetwork", "type": null}}, "importJSON": {".class": "SymbolTableNode", "cross_ref": "Precompiler.importJSON", "kind": "Gdef"}, "isolateNet": {".class": "SymbolTableNode", "cross_ref": "Precompiler.isolateNet", "kind": "Gdef"}, "setupSiteSafety": {".class": "SymbolTableNode", "cross_ref": "Precompiler.setupSiteSafety", "kind": "Gdef"}}, "path": "c:\\Users\\mpanozzo\\Documents\\GitHub\\Site-Maker-Back-End\\NetworkCrafter.py"}